yafowil.webob-1.4-nspkg.pth
yafowil/webob/__init__.py
yafowil.webob-1.4.dist-info/LICENSE.rst
yafowil.webob-1.4.dist-info/METADATA
yafowil.webob-1.4.dist-info/WHEEL
yafowil.webob-1.4.dist-info/entry_points.txt
yafowil.webob-1.4.dist-info/namespace_packages.txt
yafowil.webob-1.4.dist-info/top_level.txt
yafowil.webob-1.4.dist-info/zip-safe
yafowil.webob-1.4.dist-info/RECORD
