Metadata-Version: 2.1
Name: yafowil.webob
Version: 1.4
Summary: WebOb Integration for YAFOWIL
Home-page: http://github.com/conestack/yafowil.webob
Author: Yafowil Contributors
Author-email: dev@conestack.org
License: Simplified BSD
Keywords: webob request response html input widgets
Platform: UNKNOWN
Classifier: Operating System :: OS Independent
Classifier: Programming Language :: Python
Classifier: Topic :: Software Development
Classifier: Topic :: Internet :: WWW/HTTP :: Dynamic Content
Classifier: License :: OSI Approved :: BSD License
Requires-Dist: WebOb
Requires-Dist: setuptools
Requires-Dist: yafowil (>2.1.99)
